{
  "data": {
    "name": "Alejandro Demetrio Cortez Álvarez",
    "profession": "Full-Stack developer",
    "address": "Ciudad de México, México.",
    "email": "acortez.dev@gmail.com",
    "website": "https://zikeron.com",
    "phone": "(+52) 55 14 52 33 66",
    "avatar": "https://arepa.s3.amazonaws.com/melissa.jpg",
    "Profile": "Full-Stack developer with 5 years of experience in web application development using PHP language to develop back end and JavaScript Frameworks such as Angular, Vue JS, React to develop the front end. Currently, I am looking for an opportunity that allows me to turn around my life to keeping grow up,",
    "certificate": [
      {
        "date": "Aug 2018",
        "description": "Building PHP API's and Services using Codeigniter and Slim frameworks.',\n      'Support from many Angular v8 apps built in-house.',\n      'Management code revision history using SorceTree & Bitbucket; use JIRA boards to manage Sprint tasks.',\n      'Developing an Angular onboarding from Claro Drive.",
        "institution": "Ironbit / America Movil",
        "name": "Full Stack Developer"
      },
      {
        "date": "Jan 2021",
        "description": "Develop survey management system using Laravel 5.6 and VueJS v.2 to show a KPI's charts board.,\n      Building modules using ZendFramework for an operation in-house system.,\n      Affiliate management information analysis collection.,\n      Database administration (MySQL, MongoDB).,\n      Building collection Process & Reports.",
        "institution": "Telasist",
        "name": "Full Stack Developer"
      }
    ],
    "Academic": [
      {
        "degree": "Project Management Master",
        "description": " I’m so hungry i’m so hungry but ew not for that pelt around the house and up and down stairs chasing phantoms",
        "endDate": "Jul 2017",
        "institution": "UNITEC Campus Sur",
        "startDate": "Dec 2019"
      },
      {
        "degree": "Bachelor of Engineering in Computer Engineering",
        "description": "Meow in empty rooms. Find empty spot in cupboard and sleep all day check cat door for ambush 10 times before coming in for hack. ",
        "endDate": "Aug 2008",
        "institution": "UPIICSA - IPN",
        "startDate": "Dec 2013"
      }
    ],
    "experience": [
      {
        "company": "Ironbit / America Movil",
        "endDate": "Present",
        "jobDescription": "Building PHP API's and Services using Codeigniter and Slim frameworks.',\n      'Support from many Angular v8 apps built in-house.',\n      'Management code revision history using SorceTree & Bitbucket; use JIRA boards to manage Sprint tasks.',\n      'Developing an Angular onboarding from Claro Drive.",
        "jobTitle": "Full Stack Developer",
        "startDate": "Aug 2018"
      },
      {
        "company": "Telasist",
        "endDate": "Feb 2017",
        "jobDescription": "Develop survey management system using Laravel 5.6 and VueJS v.2 to show a KPI's charts board.,\n      Building modules using ZendFramework for an operation in-house system.,\n      Affiliate management information analysis collection.,\n      Database administration (MySQL, MongoDB).,\n      Building collection Process & Reports.",
        "jobTitle": "Full Stack Developer",
        "startDate": "Sept 2019"
      }
    ],
    "skills": [
      {
        "name": "HTML5",
        "percentage": "55%"
      },
      {
        "name": "CSS",
        "percentage": "40%"
      },
      {
        "name": "JavaScript",
        "percentage": "80%"
      },
      {
        "name": "Angular",
        "percentage": "90%"
      },
      {
        "name": "MongoDB",
        "percentage": "80%"
      },
      {
        "name": "MariaDB",
        "percentage": "80%"
      },
      {
        "name": "Redis",
        "percentage": "70%"
      },
      {
        "name": "Git",
        "percentage": "70%"
      },
      {
        "name": "NodeJS",
        "percentage": "75%"
      },
      {
        "name": "PHP",
        "percentage": "90%"
      }
    ],
    "interest": [
      "javascript",
      "develop",
      "backend",
      "frontend"
    ],
    "languages": [
      {
        "name": "Spanish",
        "percentage": "90%"
      },
      {
        "name": "English",
        "percentage": "50%"
      }
    ],
    "social": [
      {
        "name": "facebook",
        "url": "https://facebook.com/"
      },
      {
        "name": "twitter",
        "url": "https://twitter.com/ziker_on"
      },
      {
        "name": "github",
        "url": "https://github.com/zikeron"
      },
      {
        "name": "linkedin",
        "url": "https://www.linkedin.com/alejandro-cortez"
      }
    ]
  }
}
